manjpfb/CHECKSUM-SHA3-256.py
manjpfb/__init__.py
manjpfb/__main__.py
manjpfb/man_mother_mary.py
manjpfb/man_socrates.py
manjpfb/manjpfb.py
manjpfb/mman.py
manjpfb-0.0.10.dist-info/LICENSE
manjpfb-0.0.10.dist-info/METADATA
manjpfb-0.0.10.dist-info/WHEEL
manjpfb-0.0.10.dist-info/entry_points.txt
manjpfb-0.0.10.dist-info/top_level.txt
manjpfb-0.0.10.dist-info/RECORD
